[{
"id":"-3",
"alasan_layak":"Dilarang Pemda karena menerima bantuan serupa"
},
{
"id":"-2",
"alasan_layak":"Sudah Mampu"
},
{
"id":"-1",
"alasan_layak":"Menolak"
},
{
"id":"1",
"alasan_layak":"Pemegang PKH\/KPS\/KKS"
},
{
"id":"2",
"alasan_layak":"Penerima BSM 2014"
},
{
"id":"3",
"alasan_layak":"Yatim Piatu\/Panti Asuhan\/Panti Sosial"
},
{
"id":"4",
"alasan_layak":"Dampak Bencana Alam"
},
{
"id":"5",
"alasan_layak":"Pernah Drop Out"
},
{
"id":"6",
"alasan_layak":"Siswa Miskin\/Rentan Miskin"
},
{
"id":"7",
"alasan_layak":"Daerah Konflik"
},
{
"id":"8",
"alasan_layak":"Keluarga Terpidana \/ Berada di LAPAS"
},
{
"id":"9",
"alasan_layak":"Kelainan Fisik"
}
]
